odoo8_addon_website_hide-8.0.1.0.0.99.dev1-py2.7-nspkg.pth
odoo8_addon_website_hide-8.0.1.0.0.99.dev1.dist-info/METADATA
odoo8_addon_website_hide-8.0.1.0.0.99.dev1.dist-info/RECORD
odoo8_addon_website_hide-8.0.1.0.0.99.dev1.dist-info/WHEEL
odoo8_addon_website_hide-8.0.1.0.0.99.dev1.dist-info/namespace_packages.txt
odoo8_addon_website_hide-8.0.1.0.0.99.dev1.dist-info/top_level.txt
odoo_addons/website_hide/README.rst
odoo_addons/website_hide/__init__.py
odoo_addons/website_hide/__openerp__.py
odoo_addons/website_hide/hooks.py
odoo_addons/website_hide/controllers/__init__.py
odoo_addons/website_hide/controllers/main.py
odoo_addons/website_hide/data/ir_ui_menu.xml
odoo_addons/website_hide/i18n/website_hide.pot
odoo_addons/website_hide/models/__init__.py
odoo_addons/website_hide/models/ir_http.py
odoo_addons/website_hide/models/res_lang.py
odoo_addons/website_hide/static/description/icon.png
odoo_addons/website_hide/tests/__init__.py
odoo_addons/website_hide/tests/test_website_hide.py
odoo_addons/website_hide/views/templates.xml
